LICENSE.txt
MANIFEST.in
README.txt
setup.py
easy_plugins/__init__.py
easy_plugins.egg-info/PKG-INFO
easy_plugins.egg-info/SOURCES.txt
easy_plugins.egg-info/dependency_links.txt
easy_plugins.egg-info/top_level.txt