Metadata-Version: 1.0
Name: easy-plugins
Version: 1.0
Summary: Keep your plugins simple, stupid!
Home-page: https://bitbucket.org/prost87/easyplugins
Author: Stanislav Prokop
Author-email: prost87@gmail.com
License: LICENSE.txt
Platform: UNKNOWN
